[
	{
		"gateway_path": "../../galleries/new/012_dona_rosa.jpg",
		"filepath": "galleries/new/012_dona_rosa.jpg",
		"filepath_encoded": "galleries/new/012_dona_rosa.jpg",
		"dummy": "data:image/gif;base64,R0lGODlhAQABAAAAACH5BAEKAAEALAAAAAABAAEAAAICTAEAOw==",
		"gallery": "new",
		"gallery_encoded": "new",
		"dirname": "/Server/repos/minishowcase-v3/minishowcase/galleries/new",
		"basename": "012_dona_rosa.jpg",
		"basename_encoded": "012_dona_rosa.jpg",
		"extension": "jpg",
		"filename": "012_dona_rosa",
		"filename_encoded": "012_dona_rosa",
		"name": "012 dona rosa",
		"file": "012_dona_rosa.jpg",
		"file_encoded": "012_dona_rosa.jpg",
		"imagepath": "galleries/new/012_dona_rosa.jpg",
		"imagepath_encoded": "galleries/new/012_dona_rosa.jpg",
		"background_image": "galleries/new/012_dona_rosa.jpg",
		"background_image_encoded": "galleries/new/012_dona_rosa.jpg",
		"thumbs": false,
		"format": "image",
		"size": {
			"0": 400,
			"1": 263,
			"2": 2,
			"3": "width=\"400\" height=\"263\"",
			"bits": 8,
			"channels": 3,
			"mime": "image/jpeg"
		},
		"img_w": 400,
		"img_h": 263,
		"type": "JPEG"
	},
	{
		"gateway_path": "../../galleries/new/013_merida_bucare.jpg",
		"filepath": "galleries/new/013_merida_bucare.jpg",
		"filepath_encoded": "galleries/new/013_merida_bucare.jpg",
		"dummy": "data:image/gif;base64,R0lGODlhAQABAAAAACH5BAEKAAEALAAAAAABAAEAAAICTAEAOw==",
		"gallery": "new",
		"gallery_encoded": "new",
		"dirname": "/Server/repos/minishowcase-v3/minishowcase/galleries/new",
		"basename": "013_merida_bucare.jpg",
		"basename_encoded": "013_merida_bucare.jpg",
		"extension": "jpg",
		"filename": "013_merida_bucare",
		"filename_encoded": "013_merida_bucare",
		"name": "013 merida bucare",
		"file": "013_merida_bucare.jpg",
		"file_encoded": "013_merida_bucare.jpg",
		"imagepath": "galleries/new/013_merida_bucare.jpg",
		"imagepath_encoded": "galleries/new/013_merida_bucare.jpg",
		"background_image": "galleries/new/013_merida_bucare.jpg",
		"background_image_encoded": "galleries/new/013_merida_bucare.jpg",
		"thumbs": false,
		"format": "image",
		"size": {
			"0": 263,
			"1": 400,
			"2": 2,
			"3": "width=\"263\" height=\"400\"",
			"bits": 8,
			"channels": 3,
			"mime": "image/jpeg"
		},
		"img_w": 263,
		"img_h": 400,
		"type": "JPEG"
	},
	{
		"gateway_path": "../../galleries/new/014_monte_carmelo.jpg",
		"filepath": "galleries/new/014_monte_carmelo.jpg",
		"filepath_encoded": "galleries/new/014_monte_carmelo.jpg",
		"dummy": "data:image/gif;base64,R0lGODlhAQABAAAAACH5BAEKAAEALAAAAAABAAEAAAICTAEAOw==",
		"gallery": "new",
		"gallery_encoded": "new",
		"dirname": "/Server/repos/minishowcase-v3/minishowcase/galleries/new",
		"basename": "014_monte_carmelo.jpg",
		"basename_encoded": "014_monte_carmelo.jpg",
		"extension": "jpg",
		"filename": "014_monte_carmelo",
		"filename_encoded": "014_monte_carmelo",
		"name": "014 monte carmelo",
		"file": "014_monte_carmelo.jpg",
		"file_encoded": "014_monte_carmelo.jpg",
		"imagepath": "galleries/new/014_monte_carmelo.jpg",
		"imagepath_encoded": "galleries/new/014_monte_carmelo.jpg",
		"background_image": "galleries/new/014_monte_carmelo.jpg",
		"background_image_encoded": "galleries/new/014_monte_carmelo.jpg",
		"thumbs": false,
		"format": "image",
		"size": {
			"0": 400,
			"1": 263,
			"2": 2,
			"3": "width=\"400\" height=\"263\"",
			"bits": 8,
			"channels": 3,
			"mime": "image/jpeg"
		},
		"img_w": 400,
		"img_h": 263,
		"type": "JPEG"
	},
	{
		"gateway_path": "../../galleries/new/015_caribana.jpg",
		"filepath": "galleries/new/015_caribana.jpg",
		"filepath_encoded": "galleries/new/015_caribana.jpg",
		"dummy": "data:image/gif;base64,R0lGODlhAQABAAAAACH5BAEKAAEALAAAAAABAAEAAAICTAEAOw==",
		"gallery": "new",
		"gallery_encoded": "new",
		"dirname": "/Server/repos/minishowcase-v3/minishowcase/galleries/new",
		"basename": "015_caribana.jpg",
		"basename_encoded": "015_caribana.jpg",
		"extension": "jpg",
		"filename": "015_caribana",
		"filename_encoded": "015_caribana",
		"name": "015 caribana",
		"file": "015_caribana.jpg",
		"file_encoded": "015_caribana.jpg",
		"imagepath": "galleries/new/015_caribana.jpg",
		"imagepath_encoded": "galleries/new/015_caribana.jpg",
		"background_image": "galleries/new/015_caribana.jpg",
		"background_image_encoded": "galleries/new/015_caribana.jpg",
		"thumbs": false,
		"format": "image",
		"size": {
			"0": 400,
			"1": 271,
			"2": 2,
			"3": "width=\"400\" height=\"271\"",
			"bits": 8,
			"channels": 3,
			"mime": "image/jpeg"
		},
		"img_w": 400,
		"img_h": 271,
		"type": "JPEG"
	},
	{
		"gateway_path": "../../galleries/new/016_choroni.jpg",
		"filepath": "galleries/new/016_choroni.jpg",
		"filepath_encoded": "galleries/new/016_choroni.jpg",
		"dummy": "data:image/gif;base64,R0lGODlhAQABAAAAACH5BAEKAAEALAAAAAABAAEAAAICTAEAOw==",
		"gallery": "new",
		"gallery_encoded": "new",
		"dirname": "/Server/repos/minishowcase-v3/minishowcase/galleries/new",
		"basename": "016_choroni.jpg",
		"basename_encoded": "016_choroni.jpg",
		"extension": "jpg",
		"filename": "016_choroni",
		"filename_encoded": "016_choroni",
		"name": "016 choroni",
		"file": "016_choroni.jpg",
		"file_encoded": "016_choroni.jpg",
		"imagepath": "galleries/new/016_choroni.jpg",
		"imagepath_encoded": "galleries/new/016_choroni.jpg",
		"background_image": "galleries/new/016_choroni.jpg",
		"background_image_encoded": "galleries/new/016_choroni.jpg",
		"thumbs": false,
		"format": "image",
		"size": {
			"0": 400,
			"1": 269,
			"2": 2,
			"3": "width=\"400\" height=\"269\"",
			"bits": 8,
			"channels": 3,
			"mime": "image/jpeg"
		},
		"img_w": 400,
		"img_h": 269,
		"type": "JPEG"
	},
	{
		"gateway_path": "../../galleries/new/017_medina_cabins - Copy.jpg",
		"filepath": "galleries/new/017_medina_cabins - Copy.jpg",
		"filepath_encoded": "galleries/new/017_medina_cabins%20-%20Copy.jpg",
		"dummy": "data:image/gif;base64,R0lGODlhAQABAAAAACH5BAEKAAEALAAAAAABAAEAAAICTAEAOw==",
		"gallery": "new",
		"gallery_encoded": "new",
		"dirname": "/Server/repos/minishowcase-v3/minishowcase/galleries/new",
		"basename": "017_medina_cabins - Copy.jpg",
		"basename_encoded": "017_medina_cabins%20-%20Copy.jpg",
		"extension": "jpg",
		"filename": "017_medina_cabins - Copy",
		"filename_encoded": "017_medina_cabins%20-%20Copy",
		"name": "017 medina cabins - Copy",
		"file": "017_medina_cabins - Copy.jpg",
		"file_encoded": "017_medina_cabins%20-%20Copy.jpg",
		"imagepath": "galleries/new/017_medina_cabins - Copy.jpg",
		"imagepath_encoded": "galleries/new/017_medina_cabins%20-%20Copy.jpg",
		"background_image": "galleries/new/017_medina_cabins - Copy.jpg",
		"background_image_encoded": "galleries/new/017_medina_cabins%20-%20Copy.jpg",
		"thumbs": false,
		"format": "image",
		"size": {
			"0": 400,
			"1": 271,
			"2": 2,
			"3": "width=\"400\" height=\"271\"",
			"bits": 8,
			"channels": 3,
			"mime": "image/jpeg"
		},
		"img_w": 400,
		"img_h": 271,
		"type": "JPEG"
	},
	{
		"gateway_path": "../../galleries/new/017_medina_cabins.jpg",
		"filepath": "galleries/new/017_medina_cabins.jpg",
		"filepath_encoded": "galleries/new/017_medina_cabins.jpg",
		"dummy": "data:image/gif;base64,R0lGODlhAQABAAAAACH5BAEKAAEALAAAAAABAAEAAAICTAEAOw==",
		"gallery": "new",
		"gallery_encoded": "new",
		"dirname": "/Server/repos/minishowcase-v3/minishowcase/galleries/new",
		"basename": "017_medina_cabins.jpg",
		"basename_encoded": "017_medina_cabins.jpg",
		"extension": "jpg",
		"filename": "017_medina_cabins",
		"filename_encoded": "017_medina_cabins",
		"name": "017 medina cabins",
		"file": "017_medina_cabins.jpg",
		"file_encoded": "017_medina_cabins.jpg",
		"imagepath": "galleries/new/017_medina_cabins.jpg",
		"imagepath_encoded": "galleries/new/017_medina_cabins.jpg",
		"background_image": "galleries/new/017_medina_cabins.jpg",
		"background_image_encoded": "galleries/new/017_medina_cabins.jpg",
		"thumbs": false,
		"format": "image",
		"size": {
			"0": 400,
			"1": 271,
			"2": 2,
			"3": "width=\"400\" height=\"271\"",
			"bits": 8,
			"channels": 3,
			"mime": "image/jpeg"
		},
		"img_w": 400,
		"img_h": 271,
		"type": "JPEG"
	},
	{
		"gateway_path": "../../galleries/new/018_playa_medina.jpg",
		"filepath": "galleries/new/018_playa_medina.jpg",
		"filepath_encoded": "galleries/new/018_playa_medina.jpg",
		"dummy": "data:image/gif;base64,R0lGODlhAQABAAAAACH5BAEKAAEALAAAAAABAAEAAAICTAEAOw==",
		"gallery": "new",
		"gallery_encoded": "new",
		"dirname": "/Server/repos/minishowcase-v3/minishowcase/galleries/new",
		"basename": "018_playa_medina.jpg",
		"basename_encoded": "018_playa_medina.jpg",
		"extension": "jpg",
		"filename": "018_playa_medina",
		"filename_encoded": "018_playa_medina",
		"name": "018 playa medina",
		"file": "018_playa_medina.jpg",
		"file_encoded": "018_playa_medina.jpg",
		"imagepath": "galleries/new/018_playa_medina.jpg",
		"imagepath_encoded": "galleries/new/018_playa_medina.jpg",
		"background_image": "galleries/new/018_playa_medina.jpg",
		"background_image_encoded": "galleries/new/018_playa_medina.jpg",
		"thumbs": false,
		"format": "image",
		"size": {
			"0": 273,
			"1": 400,
			"2": 2,
			"3": "width=\"273\" height=\"400\"",
			"bits": 8,
			"channels": 3,
			"mime": "image/jpeg"
		},
		"img_w": 273,
		"img_h": 400,
		"type": "JPEG"
	},
	{
		"gateway_path": "../../galleries/new/019_andes - Copy.jpg",
		"filepath": "galleries/new/019_andes - Copy.jpg",
		"filepath_encoded": "galleries/new/019_andes%20-%20Copy.jpg",
		"dummy": "data:image/gif;base64,R0lGODlhAQABAAAAACH5BAEKAAEALAAAAAABAAEAAAICTAEAOw==",
		"gallery": "new",
		"gallery_encoded": "new",
		"dirname": "/Server/repos/minishowcase-v3/minishowcase/galleries/new",
		"basename": "019_andes - Copy.jpg",
		"basename_encoded": "019_andes%20-%20Copy.jpg",
		"extension": "jpg",
		"filename": "019_andes - Copy",
		"filename_encoded": "019_andes%20-%20Copy",
		"name": "019 andes - Copy",
		"file": "019_andes - Copy.jpg",
		"file_encoded": "019_andes%20-%20Copy.jpg",
		"imagepath": "galleries/new/019_andes - Copy.jpg",
		"imagepath_encoded": "galleries/new/019_andes%20-%20Copy.jpg",
		"background_image": "galleries/new/019_andes - Copy.jpg",
		"background_image_encoded": "galleries/new/019_andes%20-%20Copy.jpg",
		"thumbs": false,
		"format": "image",
		"size": {
			"0": 268,
			"1": 400,
			"2": 2,
			"3": "width=\"268\" height=\"400\"",
			"bits": 8,
			"channels": 3,
			"mime": "image/jpeg"
		},
		"img_w": 268,
		"img_h": 400,
		"type": "JPEG"
	},
	{
		"gateway_path": "../../galleries/new/020_hacha.jpg",
		"filepath": "galleries/new/020_hacha.jpg",
		"filepath_encoded": "galleries/new/020_hacha.jpg",
		"dummy": "data:image/gif;base64,R0lGODlhAQABAAAAACH5BAEKAAEALAAAAAABAAEAAAICTAEAOw==",
		"gallery": "new",
		"gallery_encoded": "new",
		"dirname": "/Server/repos/minishowcase-v3/minishowcase/galleries/new",
		"basename": "020_hacha.jpg",
		"basename_encoded": "020_hacha.jpg",
		"extension": "jpg",
		"filename": "020_hacha",
		"filename_encoded": "020_hacha",
		"name": "020 hacha",
		"file": "020_hacha.jpg",
		"file_encoded": "020_hacha.jpg",
		"imagepath": "galleries/new/020_hacha.jpg",
		"imagepath_encoded": "galleries/new/020_hacha.jpg",
		"background_image": "galleries/new/020_hacha.jpg",
		"background_image_encoded": "galleries/new/020_hacha.jpg",
		"thumbs": false,
		"format": "image",
		"size": {
			"0": 400,
			"1": 267,
			"2": 2,
			"3": "width=\"400\" height=\"267\"",
			"bits": 8,
			"channels": 3,
			"mime": "image/jpeg"
		},
		"img_w": 400,
		"img_h": 267,
		"type": "JPEG"
	},
	{
		"gateway_path": "../../galleries/new/021_los_frailes.jpg",
		"filepath": "galleries/new/021_los_frailes.jpg",
		"filepath_encoded": "galleries/new/021_los_frailes.jpg",
		"dummy": "data:image/gif;base64,R0lGODlhAQABAAAAACH5BAEKAAEALAAAAAABAAEAAAICTAEAOw==",
		"gallery": "new",
		"gallery_encoded": "new",
		"dirname": "/Server/repos/minishowcase-v3/minishowcase/galleries/new",
		"basename": "021_los_frailes.jpg",
		"basename_encoded": "021_los_frailes.jpg",
		"extension": "jpg",
		"filename": "021_los_frailes",
		"filename_encoded": "021_los_frailes",
		"name": "021 los frailes",
		"file": "021_los_frailes.jpg",
		"file_encoded": "021_los_frailes.jpg",
		"imagepath": "galleries/new/021_los_frailes.jpg",
		"imagepath_encoded": "galleries/new/021_los_frailes.jpg",
		"background_image": "galleries/new/021_los_frailes.jpg",
		"background_image_encoded": "galleries/new/021_los_frailes.jpg",
		"thumbs": false,
		"format": "image",
		"size": {
			"0": 400,
			"1": 270,
			"2": 2,
			"3": "width=\"400\" height=\"270\"",
			"bits": 8,
			"channels": 3,
			"mime": "image/jpeg"
		},
		"img_w": 400,
		"img_h": 270,
		"type": "JPEG"
	},
	{
		"gateway_path": "../../galleries/new/022_roraima_camp.jpg",
		"filepath": "galleries/new/022_roraima_camp.jpg",
		"filepath_encoded": "galleries/new/022_roraima_camp.jpg",
		"dummy": "data:image/gif;base64,R0lGODlhAQABAAAAACH5BAEKAAEALAAAAAABAAEAAAICTAEAOw==",
		"gallery": "new",
		"gallery_encoded": "new",
		"dirname": "/Server/repos/minishowcase-v3/minishowcase/galleries/new",
		"basename": "022_roraima_camp.jpg",
		"basename_encoded": "022_roraima_camp.jpg",
		"extension": "jpg",
		"filename": "022_roraima_camp",
		"filename_encoded": "022_roraima_camp",
		"name": "022 roraima camp",
		"file": "022_roraima_camp.jpg",
		"file_encoded": "022_roraima_camp.jpg",
		"imagepath": "galleries/new/022_roraima_camp.jpg",
		"imagepath_encoded": "galleries/new/022_roraima_camp.jpg",
		"background_image": "galleries/new/022_roraima_camp.jpg",
		"background_image_encoded": "galleries/new/022_roraima_camp.jpg",
		"thumbs": false,
		"format": "image",
		"size": {
			"0": 400,
			"1": 262,
			"2": 2,
			"3": "width=\"400\" height=\"262\"",
			"bits": 8,
			"channels": 3,
			"mime": "image/jpeg"
		},
		"img_w": 400,
		"img_h": 262,
		"type": "JPEG"
	},
	{
		"gateway_path": "../../galleries/new/023_roraima_edge.jpg",
		"filepath": "galleries/new/023_roraima_edge.jpg",
		"filepath_encoded": "galleries/new/023_roraima_edge.jpg",
		"dummy": "data:image/gif;base64,R0lGODlhAQABAAAAACH5BAEKAAEALAAAAAABAAEAAAICTAEAOw==",
		"gallery": "new",
		"gallery_encoded": "new",
		"dirname": "/Server/repos/minishowcase-v3/minishowcase/galleries/new",
		"basename": "023_roraima_edge.jpg",
		"basename_encoded": "023_roraima_edge.jpg",
		"extension": "jpg",
		"filename": "023_roraima_edge",
		"filename_encoded": "023_roraima_edge",
		"name": "023 roraima edge",
		"file": "023_roraima_edge.jpg",
		"file_encoded": "023_roraima_edge.jpg",
		"imagepath": "galleries/new/023_roraima_edge.jpg",
		"imagepath_encoded": "galleries/new/023_roraima_edge.jpg",
		"background_image": "galleries/new/023_roraima_edge.jpg",
		"background_image_encoded": "galleries/new/023_roraima_edge.jpg",
		"thumbs": false,
		"format": "image",
		"size": {
			"0": 400,
			"1": 263,
			"2": 2,
			"3": "width=\"400\" height=\"263\"",
			"bits": 8,
			"channels": 3,
			"mime": "image/jpeg"
		},
		"img_w": 400,
		"img_h": 263,
		"type": "JPEG"
	},
	{
		"gateway_path": "../../galleries/new/024_roraima_hotel.jpg",
		"filepath": "galleries/new/024_roraima_hotel.jpg",
		"filepath_encoded": "galleries/new/024_roraima_hotel.jpg",
		"dummy": "data:image/gif;base64,R0lGODlhAQABAAAAACH5BAEKAAEALAAAAAABAAEAAAICTAEAOw==",
		"gallery": "new",
		"gallery_encoded": "new",
		"dirname": "/Server/repos/minishowcase-v3/minishowcase/galleries/new",
		"basename": "024_roraima_hotel.jpg",
		"basename_encoded": "024_roraima_hotel.jpg",
		"extension": "jpg",
		"filename": "024_roraima_hotel",
		"filename_encoded": "024_roraima_hotel",
		"name": "024 roraima hotel",
		"file": "024_roraima_hotel.jpg",
		"file_encoded": "024_roraima_hotel.jpg",
		"imagepath": "galleries/new/024_roraima_hotel.jpg",
		"imagepath_encoded": "galleries/new/024_roraima_hotel.jpg",
		"background_image": "galleries/new/024_roraima_hotel.jpg",
		"background_image_encoded": "galleries/new/024_roraima_hotel.jpg",
		"thumbs": false,
		"format": "image",
		"size": {
			"0": 268,
			"1": 400,
			"2": 2,
			"3": "width=\"268\" height=\"400\"",
			"bits": 8,
			"channels": 3,
			"mime": "image/jpeg"
		},
		"img_w": 268,
		"img_h": 400,
		"type": "JPEG"
	}
]